setup.py
nrf24lu1_boot/__init__.py
nrf24lu1_boot.egg-info/PKG-INFO
nrf24lu1_boot.egg-info/SOURCES.txt
nrf24lu1_boot.egg-info/dependency_links.txt
nrf24lu1_boot.egg-info/not-zip-safe
nrf24lu1_boot.egg-info/requires.txt
nrf24lu1_boot.egg-info/top_level.txt