Metadata-Version: 1.0
Name: nrf24lu1-boot
Version: 0.0.0
Summary: Python library for controlling the nrf24lu1p-512-bootloader.
Home-page: https://github.com/ahtn/nrf24lu1p-512-bootloader
Author: jem
Author-email: jem@seethis.link
License: MIT
Keywords: nrf24lu1+,usb,hid,bootloader
Platform: UNKNOWN
